lmoe/__init__.py
lmoe/api/__init__.py
lmoe/api/base_expert.py
lmoe/api/lmoe_query.py
lmoe/api/model.py
lmoe/api/model_expert.py
lmoe/commands/__init__.py
lmoe/commands/cleanup.py
lmoe/commands/command.py
lmoe/commands/command_runner.py
lmoe/commands/initialize.py
lmoe/commands/passthrough.py
lmoe/commands/print_classification.py
lmoe/commands/print_classifier_modelfile.py
lmoe/commands/query.py
lmoe/commands/refresh.py
lmoe/commands/version.py
lmoe/definitions.py
lmoe/experts/__init__.py
lmoe/experts/classifier.py
lmoe/experts/code.py
lmoe/experts/general.py
lmoe/experts/image.py
lmoe/experts/list_models.py
lmoe/experts/personality.py
lmoe/experts/project_initialization.py
lmoe/experts/refresh.py
lmoe/framework/__init__.py
lmoe/framework/config.py
lmoe/framework/expert_registry.py
lmoe/framework/lmoe_logger.py
lmoe/framework/model_registry.py
lmoe/framework/module_loader.py
lmoe/framework/native_module.py
lmoe/framework/ollama_client.py
lmoe/framework/plugin_module_registry.py
lmoe/main.py
lmoe/release.py
lmoe/templates/__init__.py
lmoe/templates/classifier.modelfile.txt
lmoe/templates/code.modelfile.txt
lmoe/templates/general.modelfile.txt
lmoe/templates/image.modelfile.txt
lmoe/templates/personality.examples.yaml
lmoe/templates/personality.modelfile.txt
lmoe/templates/project_initialization.modelfile.txt
lmoe/utils/__init__.py
lmoe/utils/dict_utils.py
lmoe/utils/templates.py
lmoe-0.3.18.dist-info/entry_points.txt
lmoe-0.3.18.dist-info/LICENSE
lmoe-0.3.18.dist-info/WHEEL
lmoe-0.3.18.dist-info/METADATA
lmoe-0.3.18.dist-info/RECORD
