Metadata-Version: 2.1
Name: lmoe
Version: 0.3.18
Summary: lmoe (Layered Mixture of Experts,'Elmo') is your programmable CLI assistant.
Author: Ryan Eiger
Author-email: ryebosome@gmail.com
Requires-Python: >=3.9,<4.0
Classifier: Programming Language :: Python :: 3
Classifier: Programming Language :: Python :: 3.9
Classifier: Programming Language :: Python :: 3.10
Requires-Dist: PySocks (>=1.7.1,<2.0.0)
Requires-Dist: PyYAML (>=6.0.1,<7.0.0)
Requires-Dist: injector (>=0.21.0,<0.22.0)
Requires-Dist: ollama (>=0.1.6,<0.2.0)
Requires-Dist: pyperclip (>=1.8.2,<2.0.0)
Requires-Dist: pytest (>=8.0.1,<9.0.0)
Requires-Dist: pytype (>=2024.1.24,<2025.0.0)
Requires-Dist: requests (>=2.31.0,<3.0.0)
Requires-Dist: semantic-version (>=2.10.0,<3.0.0)
Requires-Dist: urllib3 (==1.26.15)
